translang/__init__.py
translang/core.py
translang-0.1.4.dist-info/LICENSE
translang-0.1.4.dist-info/METADATA
translang-0.1.4.dist-info/WHEEL
translang-0.1.4.dist-info/entry_points.txt
translang-0.1.4.dist-info/top_level.txt
translang-0.1.4.dist-info/RECORD
