Metadata-Version: 2.1
Name: translang
Version: 0.1.4
Summary: Translation Service API Module.
Home-page: https://github.com/dsdanielpark/hf-transllm
Author: daniel park
Author-email: parkminwoo1991@gmail.com
Keywords: Python,API,Bard,Google Bard,Large Language Model,Chatbot API,Google API,Chatbot
Classifier: Development Status :: 3 - Alpha
Classifier: Intended Audience :: Science/Research
Classifier: Natural Language :: English
Classifier: Programming Language :: Python
Classifier: Programming Language :: Python :: 3.6
Classifier: Programming Language :: Python :: 3.7
Classifier: Programming Language :: Python :: 3.8
Classifier: License :: OSI Approved :: MIT License
Classifier: Programming Language :: Python :: 3.6
Classifier: Topic :: Scientific/Engineering :: Artificial Intelligence
Requires-Python: >=3.6
License-File: LICENSE
Requires-Dist: requests
Requires-Dist: deepl
Requires-Dist: deep-translator
Requires-Dist: bardapi
Requires-Dist: openai
Requires-Dist: google-cloud-translate (==2.0.1)
